hayhooks/__init__.py
hayhooks/__main__.py
hayhooks/callbacks.py
hayhooks/open_webui.py
hayhooks/settings.py
hayhooks/cli/__init__.py
hayhooks/cli/base.py
hayhooks/cli/mcp.py
hayhooks/cli/pipeline.py
hayhooks/cli/utils.py
hayhooks/server/__init__.py
hayhooks/server/app.py
hayhooks/server/exceptions.py
hayhooks/server/logger.py
hayhooks/server/pipelines/__init__.py
hayhooks/server/pipelines/models.py
hayhooks/server/pipelines/registry.py
hayhooks/server/pipelines/sse.py
hayhooks/server/pipelines/streaming.py
hayhooks/server/pipelines/utils.py
hayhooks/server/routers/__init__.py
hayhooks/server/routers/deploy.py
hayhooks/server/routers/draw.py
hayhooks/server/routers/openai.py
hayhooks/server/routers/status.py
hayhooks/server/routers/undeploy.py
hayhooks/server/utils/__init__.py
hayhooks/server/utils/base_pipeline_wrapper.py
hayhooks/server/utils/deploy_utils.py
hayhooks/server/utils/mcp_utils.py
hayhooks/server/utils/module_loader.py
hayhooks/server/utils/yaml_utils.py
hayhooks/testing/__init__.py
hayhooks/testing/components.py
hayhooks-1.9.0.dist-info/METADATA
hayhooks-1.9.0.dist-info/WHEEL
hayhooks-1.9.0.dist-info/entry_points.txt
hayhooks-1.9.0.dist-info/licenses/LICENSE
hayhooks-1.9.0.dist-info/RECORD
