Metadata-Version: 2.4
Name: hayhooks
Version: 1.9.0
Summary: Grab and deploy Haystack pipelines
Project-URL: Documentation, https://github.com/deepset-ai/hayhooks#readme
Project-URL: Issues, https://github.com/deepset-ai/hayhooks/issues
Project-URL: Source, https://github.com/deepset-ai/hayhooks
Author-email: "deepset.ai" <malte.pietsch@deepset.ai>
License-Expression: Apache-2.0
License-File: LICENSE
Classifier: Development Status :: 4 - Beta
Classifier: Programming Language :: Python
Classifier: Programming Language :: Python :: 3.10
Classifier: Programming Language :: Python :: 3.11
Classifier: Programming Language :: Python :: 3.12
Classifier: Programming Language :: Python :: 3.13
Classifier: Programming Language :: Python :: 3.14
Classifier: Programming Language :: Python :: Implementation :: CPython
Classifier: Programming Language :: Python :: Implementation :: PyPy
Requires-Python: <3.15,>=3.10
Requires-Dist: docstring-parser
Requires-Dist: fastapi[standard]
Requires-Dist: haystack-ai!=2.18.0
Requires-Dist: loguru
Requires-Dist: pydantic-settings
Requires-Dist: python-dotenv
Requires-Dist: python-multipart
Requires-Dist: requests
Requires-Dist: rich
Requires-Dist: typer
Requires-Dist: uvicorn
Provides-Extra: mcp
Requires-Dist: mcp>=1.8.0; (python_version >= '3.10') and extra == 'mcp'
